LICENSE
README.md
setup.py
payday/__init__.py
payday/bash.py
payday/c.py
payday/curl.py
payday/netcat.py
payday/perl.py
payday.egg-info/PKG-INFO
payday.egg-info/SOURCES.txt
payday.egg-info/dependency_links.txt
payday.egg-info/top_level.txt