Metadata-Version: 2.4
Name: payday
Version: 0.1.0
Summary: a library for generating bind and reverse shell payloads across a disverse set of platforms
Author: lewis patten
Author-email: lpatten1729@gmail.com
Maintainer: lewis patten
Maintainer-email: lpatten1729@gmail.com
License: GPL2
License-File: LICENSE
Dynamic: author
Dynamic: author-email
Dynamic: license
Dynamic: license-file
Dynamic: maintainer
Dynamic: maintainer-email
Dynamic: summary
